report_generation_utils/__init__.py
report_generation_utils/console_helper.py
report_generation_utils/constants.py
report_generation_utils/file_utils.py
report_generation_utils/generate_report.py
report_generation_utils/manager.py
report_generation_utils/system_caller.py
report_generation_utils/conf/config.yaml
report_generation_utils-0.1.1.dist-info/AUTHORS.rst
report_generation_utils-0.1.1.dist-info/METADATA
report_generation_utils-0.1.1.dist-info/WHEEL
report_generation_utils-0.1.1.dist-info/entry_points.txt
report_generation_utils-0.1.1.dist-info/top_level.txt
report_generation_utils-0.1.1.dist-info/RECORD
