Metadata-Version: 2.1
Name: report_generation_utils
Version: 0.1.1
Summary: Collection of Python tools for generating reports in various formats.
Home-page: https://github.com/jai-python3/report-generation-utils
Author: Jaideep Sundaram
Author-email: jai.python3@gmail.com
Keywords: report_generation_utils
Classifier: Development Status :: 2 - Pre-Alpha
Classifier: Intended Audience :: Developers
Classifier: Natural Language :: English
Classifier: Programming Language :: Python :: 3
Classifier: Programming Language :: Python :: 3.6
Classifier: Programming Language :: Python :: 3.7
Classifier: Programming Language :: Python :: 3.8
Requires-Python: >=3.6
License-File: AUTHORS.rst
Requires-Dist: Click >=7.0
Requires-Dist: jinja2
Requires-Dist: PyYAML
Requires-Dist: Rich
